treesp/__init__.py
treesp/treesp.py
treesp-1.0.2.dist-info/LICENSE
treesp-1.0.2.dist-info/METADATA
treesp-1.0.2.dist-info/WHEEL
treesp-1.0.2.dist-info/top_level.txt
treesp-1.0.2.dist-info/RECORD
