Metadata-Version: 2.1
Name: treesp
Version: 1.0.2
Summary: trees
Home-page: UNKNOWN
Author: Sidharth Parekh
Author-email: sidharthparekh1@gmail.com
License: UNKNOWN
Keywords: python,preorder,postorder,inorder,trees
Platform: UNKNOWN
Classifier: Development Status :: 1 - Planning
Classifier: Intended Audience :: Developers
Classifier: Programming Language :: Python :: 3
Classifier: Operating System :: Unix
Classifier: Operating System :: MacOS :: MacOS X
Classifier: Operating System :: Microsoft :: Windows
License-File: LICENSE
